dockerfile.abi3.h
dockerfile.abi3.so
dockerfile-3.4.0.dist-info/LICENSE
dockerfile-3.4.0.dist-info/METADATA
dockerfile-3.4.0.dist-info/WHEEL
dockerfile-3.4.0.dist-info/top_level.txt
dockerfile-3.4.0.dist-info/RECORD
