Metadata-Version: 2.1
Name: dockerfile
Version: 3.4.0
Summary: Parse a dockerfile into a high-level representation using the official go parser.
Home-page: https://github.com/asottile/dockerfile
Author: Anthony Sottile
Author-email: asottile@umich.edu
License: MIT
Classifier: License :: OSI Approved :: MIT License
Classifier: Programming Language :: Python :: 3
Classifier: Programming Language :: Python :: 3 :: Only
Classifier: Programming Language :: Python :: Implementation :: CPython
Classifier: Programming Language :: Python :: Implementation :: PyPy
Requires-Python: >=3.9
License-File: LICENSE
